TijaToolsProgressRing/__init__.py
TijaToolsProgressRing/progress_ring.py
TijaToolsProgressRing/tijatools_terminal_progress_ring_tests.py
TijaToolsProgressRing-0.1.0.dist-info/LICENSE
TijaToolsProgressRing-0.1.0.dist-info/METADATA
TijaToolsProgressRing-0.1.0.dist-info/WHEEL
TijaToolsProgressRing-0.1.0.dist-info/top_level.txt
TijaToolsProgressRing-0.1.0.dist-info/RECORD
